prism_abstract_library/I_API.py
prism_abstract_library/I_Database.py
prism_abstract_library/I_Endpoint.py
prism_abstract_library/I_Endpoints.py
prism_abstract_library/I_Table.py
prism_abstract_library/__init__.py
prism_abstract_library-0.1.1.dist-info/METADATA
prism_abstract_library-0.1.1.dist-info/WHEEL
prism_abstract_library-0.1.1.dist-info/RECORD
