Metadata-Version: 2.1
Name: prism-abstract-library
Version: 0.1.1
Summary: Base classes and shared API endpoints for PRISM
Author: Isaac
Author-email: isummers@bastiansolutions.com
Requires-Python: >=3.10,<4.0
Classifier: Programming Language :: Python :: 3
Classifier: Programming Language :: Python :: 3.10
Classifier: Programming Language :: Python :: 3.11
Classifier: Programming Language :: Python :: 3.12
Requires-Dist: fastapi (>=0.111.1,<0.112.0)
Requires-Dist: sqlalchemy (>=2.0.31,<3.0.0)
